sqldq/__init__.py
sqldq/py.typed
sqldq/sqldq.py
sqldq-0.2.6.dist-info/licenses/LICENSE
sqldq-0.2.6.dist-info/WHEEL
sqldq-0.2.6.dist-info/METADATA
sqldq-0.2.6.dist-info/RECORD
