Metadata-Version: 2.4
Name: sqldq
Version: 0.2.6
Summary: Data Quality checks using SQL
Author: Dominik Schauer
Requires-Python: >=3.10
License-File: LICENSE
Requires-Dist: awswrangler>=3.12.1
Requires-Dist: boto3>=1.39.4
Requires-Dist: pandas>=2.3.1
Requires-Dist: polars[pyarrow]>=1.31.0
Project-URL: Documentation, https://hyperdq.github.io/sqldq/
Project-URL: Homepage, https://github.com/hyperdq/sqldq
Project-URL: Repository, https://github.com/hyperdq/sqldq
